pylon/__init__.py
pylon/_client.py
pylon/_http.py
pylon/_version.py
pylon/exceptions.py
pylon/filters.py
pylon/py.typed
pylon/models/__init__.py
pylon/models/accounts.py
pylon/models/activities.py
pylon/models/attachments.py
pylon/models/audit_logs.py
pylon/models/base.py
pylon/models/contacts.py
pylon/models/custom_fields.py
pylon/models/files.py
pylon/models/highlights.py
pylon/models/issues.py
pylon/models/knowledge_base.py
pylon/models/me.py
pylon/models/messages.py
pylon/models/pagination.py
pylon/models/projects.py
pylon/models/tags.py
pylon/models/tasks.py
pylon/models/teams.py
pylon/models/ticket_forms.py
pylon/models/user_roles.py
pylon/models/users.py
pylon/resources/__init__.py
pylon/resources/_base.py
pylon/resources/_bound.py
pylon/resources/_pagination.py
pylon/resources/accounts.py
pylon/resources/attachments.py
pylon/resources/audit_logs.py
pylon/resources/contacts.py
pylon/resources/custom_fields.py
pylon/resources/issues.py
pylon/resources/knowledge_base.py
pylon/resources/me.py
pylon/resources/messages.py
pylon/resources/projects.py
pylon/resources/tags.py
pylon/resources/tasks.py
pylon/resources/teams.py
pylon/resources/ticket_forms.py
pylon/resources/user_roles.py
pylon/resources/users.py
pylon/resources/bound/__init__.py
pylon/resources/bound/account_activities.py
pylon/resources/bound/account_files.py
pylon/resources/bound/account_highlights.py
pylon/resources/bound/issue_attachments.py
pylon/resources/bound/issue_messages.py
pylon/webhooks/__init__.py
pylon/webhooks/events.py
pylon/webhooks/handler.py
py_usepylon_sdk-0.5.0.dist-info/METADATA
py_usepylon_sdk-0.5.0.dist-info/WHEEL
py_usepylon_sdk-0.5.0.dist-info/licenses/LICENSE
py_usepylon_sdk-0.5.0.dist-info/RECORD
