Metadata-Version: 2.4
Name: py-usepylon-sdk
Version: 0.5.0
Summary: A modern Python SDK for the Pylon customer support API
Project-URL: Homepage, https://github.com/mgmonteleone/py-usepylon-sdk
Project-URL: Documentation, https://github.com/mgmonteleone/py-usepylon-sdk#readme
Project-URL: Repository, https://github.com/mgmonteleone/py-usepylon-sdk.git
Project-URL: Issues, https://github.com/mgmonteleone/py-usepylon-sdk/issues
Project-URL: Changelog, https://github.com/mgmonteleone/py-usepylon-sdk/blob/main/CHANGELOG.md
Author-email: "Matthew G. Monteleone" <matthewm@augmentcode.com>
License-Expression: MIT
License-File: LICENSE
Keywords: api,customer-support,helpdesk,pylon,sdk
Classifier: Development Status :: 3 - Alpha
Classifier: Intended Audience :: Developers
Classifier: License :: OSI Approved :: MIT License
Classifier: Operating System :: OS Independent
Classifier: Programming Language :: Python :: 3
Classifier: Programming Language :: Python :: 3.11
Classifier: Programming Language :: Python :: 3.12
Classifier: Programming Language :: Python :: 3.13
Classifier: Topic :: Software Development :: Libraries :: Python Modules
Classifier: Typing :: Typed
Requires-Python: >=3.11
Requires-Dist: httpx>=0.25.0
Requires-Dist: pydantic>=2.0
Requires-Dist: tenacity>=8.0
Provides-Extra: dev
Requires-Dist: mypy>=1.7.0; extra == 'dev'
Requires-Dist: pytest-asyncio>=0.21.0; extra == 'dev'
Requires-Dist: pytest-cov>=4.1.0; extra == 'dev'
Requires-Dist: pytest>=7.4.0; extra == 'dev'
Requires-Dist: respx>=0.20.0; extra == 'dev'
Requires-Dist: ruff>=0.1.0; extra == 'dev'
Provides-Extra: docs
Requires-Dist: mkdocs-material>=9.5.0; extra == 'docs'
Requires-Dist: mkdocs>=1.5.0; extra == 'docs'
Requires-Dist: mkdocstrings[python]>=0.24.0; extra == 'docs'
